{
    "destination_addresses": [
        "2506 River Dr, Knoxville, TN 37996, USA",
        "1521 University Ave, Knoxville, TN 37921, USA",
        "1610 University Ave, Knoxville, TN 37921, USA",
        "1817 Melrose Avenue, 1817 Melrose Ave, Knoxville, TN 37916, USA",
        "2101 Terrace Ave, Knoxville, TN 37996, USA",
        "2106 Terrace Ave, Knoxville, TN 37916, USA",
        "2110 Terrace Ave, Knoxville, TN 37996, USA",
        "2111 Stephenson Dr, Knoxville, TN 37916, USA",
        "913 22nd St, Knoxville, TN 37916, USA",
        "908 S 21st St, Knoxville, TN 37916, USA"
    ],
    "origin_addresses": [
        "2007 Lake Ave, Knoxville, TN 37916, USA",
        "909 Mountcastle St SW, Knoxville, TN 37916, USA",
        "2117 Andy Holt Ave, Knoxville, TN 37916, USA",
        "1838 Terrace Ave, Knoxville, TN 37916, USA",
        "714 W Hill Ave, Knoxville, TN 37902, USA",
        "2501 University Commons Way, Knoxville, TN 37996, USA",
        "2710 Neyland Dr, Knoxville, TN 37919, USA",
        "2307 Clinch Ave, Knoxville, TN 37916, USA"
    ],
    "rows": [
        {
            "elements": [
                {
                    "distance": {
                        "text": "1.3 km",
                        "value": 1259
                    },
                    "duration": {
                        "text": "16 mins",
                        "value": 942
                    },
                    "status": "OK"
                },
                {
                    "distance": {
                        "text": "2.2 km",
                        "value": 2174
                    },
                    "duration": {
                        "text": "29 mins",
                        "value": 1759
                    },
                    "status": "OK"
                },
                {
                    "distance": {
                        "text": "2.1 km",
                        "value": 2079
                    },
                    "duration": {
                        "text": "28 mins",
                        "value": 1681
                    },
                    "status": "OK"
                },
                {
                    "distance": {
                        "text": "0.5 km",
                        "value": 477
                    },
                    "duration": {
                        "text": "7 mins",
                        "value": 439
                    },
                    "status": "OK"
                },
                {
                    "distance": {
                        "text": "0.2 km",
                        "value": 243
                    },
                    "duration": {
                        "text": "3 mins",
                        "value": 205
                    },
                    "status": "OK"
                },
                {
                    "distance": {
                        "text": "0.4 km",
                        "value": 442
                    },
                    "duration": {
                        "text": "6 mins",
                        "value": 375
                    },
                    "status": "OK"
                },
                {
                    "distance": {
                        "text": "0.3 km",
                        "value": 287
                    },
                    "duration": {
                        "text": "4 mins",
                        "value": 234
                    },
                    "status": "OK"
                },
                {
                    "distance": {
                        "text": "2.5 km",
                        "value": 2452
                    },
                    "duration": {
                        "text": "31 mins",
                        "value": 1837
                    },
                    "status": "OK"
                },
                {
                    "distance": {
                        "text": "0.3 km",
                        "value": 281
                    },
                    "duration": {
                        "text": "4 mins",
                        "value": 211
                    },
                    "status": "OK"
                },
                {
                    "distance": {
                        "text": "0.2 km",
                        "value": 154
                    },
                    "duration": {
                        "text": "2 mins",
                        "value": 117
                    },
                    "status": "OK"
                }
            ]
        },
        {
            "elements": [
                {
                    "distance": {
                        "text": "1.2 km",
                        "value": 1230
                    },
                    "duration": {
                        "text": "15 mins",
                        "value": 923
                    },
                    "status": "OK"
                },
                {
                    "distance": {
                        "text": "2.2 km",
                        "value": 2223
                    },
                    "duration": {
                        "text": "30 mins",
                        "value": 1790
                    },
                    "status": "OK"
                },
                {
                    "distance": {
                        "text": "2.1 km",
                        "value": 2128
                    },
                    "duration": {
                        "text": "29 mins",
                        "value": 1712
                    },
                    "status": "OK"
                },
                {
                    "distance": {
                        "text": "0.4 km",
                        "value": 369
                    },
                    "duration": {
                        "text": "6 mins",
                        "value": 340
                    },
                    "status": "OK"
                },
                {
                    "distance": {
                        "text": "0.2 km",
                        "value": 248
                    },
                    "duration": {
                        "text": "3 mins",
                        "value": 186
                    },
                    "status": "OK"
                },
                {
                    "distance": {
                        "text": "0.3 km",
                        "value": 337
                    },
                    "duration": {
                        "text": "5 mins",
                        "value": 275
                    },
                    "status": "OK"
                },
                {
                    "distance": {
                        "text": "0.3 km",
                        "value": 293
                    },
                    "duration": {
                        "text": "4 mins",
                        "value": 216
                    },
                    "status": "OK"
                },
                {
                    "distance": {
                        "text": "2.4 km",
                        "value": 2423
                    },
                    "duration": {
                        "text": "30 mins",
                        "value": 1818
                    },
                    "status": "OK"
                },
                {
                    "distance": {
                        "text": "0.3 km",
                        "value": 330
                    },
                    "duration": {
                        "text": "4 mins",
                        "value": 250
                    },
                    "status": "OK"
                },
                {
                    "distance": {
                        "text": "0.2 km",
                        "value": 203
                    },
                    "duration": {
                        "text": "3 mins",
                        "value": 152
                    },
                    "status": "OK"
                }
            ]
        },
        {
            "elements": [
                {
                    "distance": {
                        "text": "0.8 km",
                        "value": 783
                    },
                    "duration": {
                        "text": "9 mins",
                        "value": 552
                    },
                    "status": "OK"
                },
                {
                    "distance": {
                        "text": "2.5 km",
                        "value": 2521
                    },
                    "duration": {
                        "text": "33 mins",
                        "value": 1980
                    },
                    "status": "OK"
                },
                {
                    "distance": {
                        "text": "2.4 km",
                        "value": 2426
                    },
                    "duration": {
                        "text": "32 mins",
                        "value": 1902
                    },
                    "status": "OK"
                },
                {
                    "distance": {
                        "text": "0.6 km",
                        "value": 560
                    },
                    "duration": {
                        "text": "7 mins",
                        "value": 443
                    },
                    "status": "OK"
                },
                {
                    "distance": {
                        "text": "0.4 km",
                        "value": 354
                    },
                    "duration": {
                        "text": "4 mins",
                        "value": 250
                    },
                    "status": "OK"
                },
                {
                    "distance": {
                        "text": "0.3 km",
                        "value": 308
                    },
                    "duration": {
                        "text": "4 mins",
                        "value": 217
                    },
                    "status": "OK"
                },
                {
                    "distance": {
                        "text": "0.4 km",
                        "value": 398
                    },
                    "duration": {
                        "text": "5 mins",
                        "value": 280
                    },
                    "status": "OK"
                },
                {
                    "distance": {
                        "text": "2.0 km",
                        "value": 1976
                    },
                    "duration": {
                        "text": "24 mins",
                        "value": 1437
                    },
                    "status": "OK"
                },
                {
                    "distance": {
                        "text": "0.5 km",
                        "value": 482
                    },
                    "duration": {
                        "text": "6 mins",
                        "value": 341
                    },
                    "status": "OK"
                },
                {
                    "distance": {
                        "text": "0.4 km",
                        "value": 404
                    },
                    "duration": {
                        "text": "5 mins",
                        "value": 286
                    },
                    "status": "OK"
                }
            ]
        },
        {
            "elements": [
                {
                    "distance": {
                        "text": "1.3 km",
                        "value": 1288
                    },
                    "duration": {
                        "text": "16 mins",
                        "value": 952
                    },
                    "status": "OK"
                },
                {
                    "distance": {
                        "text": "2.0 km",
                        "value": 2050
                    },
                    "duration": {
                        "text": "27 mins",
                        "value": 1627
                    },
                    "status": "OK"
                },
                {
                    "distance": {
                        "text": "2.0 km",
                        "value": 1955
                    },
                    "duration": {
                        "text": "26 mins",
                        "value": 1549
                    },
                    "status": "OK"
                },
                {
                    "distance": {
                        "text": "0.1 km",
                        "value": 137
                    },
                    "duration": {
                        "text": "2 mins",
                        "value": 133
                    },
                    "status": "OK"
                },
                {
                    "distance": {
                        "text": "0.4 km",
                        "value": 362
                    },
                    "duration": {
                        "text": "4 mins",
                        "value": 248
                    },
                    "status": "OK"
                },
                {
                    "distance": {
                        "text": "0.4 km",
                        "value": 412
                    },
                    "duration": {
                        "text": "5 mins",
                        "value": 299
                    },
                    "status": "OK"
                },
                {
                    "distance": {
                        "text": "0.4 km",
                        "value": 406
                    },
                    "duration": {
                        "text": "5 mins",
                        "value": 277
                    },
                    "status": "OK"
                },
                {
                    "distance": {
                        "text": "2.3 km",
                        "value": 2294
                    },
                    "duration": {
                        "text": "28 mins",
                        "value": 1693
                    },
                    "status": "OK"
                },
                {
                    "distance": {
                        "text": "0.5 km",
                        "value": 490
                    },
                    "duration": {
                        "text": "6 mins",
                        "value": 338
                    },
                    "status": "OK"
                },
                {
                    "distance": {
                        "text": "0.4 km",
                        "value": 412
                    },
                    "duration": {
                        "text": "5 mins",
                        "value": 284
                    },
                    "status": "OK"
                }
            ]
        },
        {
            "elements": [
                {
                    "distance": {
                        "text": "2.8 km",
                        "value": 2794
                    },
                    "duration": {
                        "text": "35 mins",
                        "value": 2105
                    },
                    "status": "OK"
                },
                {
                    "distance": {
                        "text": "2.3 km",
                        "value": 2310
                    },
                    "duration": {
                        "text": "30 mins",
                        "value": 1792
                    },
                    "status": "OK"
                },
                {
                    "distance": {
                        "text": "2.4 km",
                        "value": 2360
                    },
                    "duration": {
                        "text": "30 mins",
                        "value": 1811
                    },
                    "status": "OK"
                },
                {
                    "distance": {
                        "text": "1.7 km",
                        "value": 1667
                    },
                    "duration": {
                        "text": "22 mins",
                        "value": 1340
                    },
                    "status": "OK"
                },
                {
                    "distance": {
                        "text": "2.0 km",
                        "value": 2004
                    },
                    "duration": {
                        "text": "25 mins",
                        "value": 1518
                    },
                    "status": "OK"
                },
                {
                    "distance": {
                        "text": "2.1 km",
                        "value": 2102
                    },
                    "duration": {
                        "text": "27 mins",
                        "value": 1629
                    },
                    "status": "OK"
                },
                {
                    "distance": {
                        "text": "2.0 km",
                        "value": 2049
                    },
                    "duration": {
                        "text": "26 mins",
                        "value": 1548
                    },
                    "status": "OK"
                },
                {
                    "distance": {
                        "text": "2.5 km",
                        "value": 2522
                    },
                    "duration": {
                        "text": "31 mins",
                        "value": 1842
                    },
                    "status": "OK"
                },
                {
                    "distance": {
                        "text": "2.1 km",
                        "value": 2089
                    },
                    "duration": {
                        "text": "26 mins",
                        "value": 1572
                    },
                    "status": "OK"
                },
                {
                    "distance": {
                        "text": "2.0 km",
                        "value": 1966
                    },
                    "duration": {
                        "text": "25 mins",
                        "value": 1487
                    },
                    "status": "OK"
                }
            ]
        },
        {
            "elements": [
                {
                    "distance": {
                        "text": "0.9 km",
                        "value": 863
                    },
                    "duration": {
                        "text": "11 mins",
                        "value": 657
                    },
                    "status": "OK"
                },
                {
                    "distance": {
                        "text": "2.9 km",
                        "value": 2935
                    },
                    "duration": {
                        "text": "38 mins",
                        "value": 2296
                    },
                    "status": "OK"
                },
                {
                    "distance": {
                        "text": "2.8 km",
                        "value": 2832
                    },
                    "duration": {
                        "text": "37 mins",
                        "value": 2217
                    },
                    "status": "OK"
                },
                {
                    "distance": {
                        "text": "1.4 km",
                        "value": 1384
                    },
                    "duration": {
                        "text": "20 mins",
                        "value": 1173
                    },
                    "status": "OK"
                },
                {
                    "distance": {
                        "text": "0.9 km",
                        "value": 937
                    },
                    "duration": {
                        "text": "13 mins",
                        "value": 760
                    },
                    "status": "OK"
                },
                {
                    "distance": {
                        "text": "1.1 km",
                        "value": 1055
                    },
                    "duration": {
                        "text": "14 mins",
                        "value": 854
                    },
                    "status": "OK"
                },
                {
                    "distance": {
                        "text": "0.9 km",
                        "value": 893
                    },
                    "duration": {
                        "text": "12 mins",
                        "value": 727
                    },
                    "status": "OK"
                },
                {
                    "distance": {
                        "text": "1.9 km",
                        "value": 1916
                    },
                    "duration": {
                        "text": "24 mins",
                        "value": 1416
                    },
                    "status": "OK"
                },
                {
                    "distance": {
                        "text": "0.8 km",
                        "value": 809
                    },
                    "duration": {
                        "text": "11 mins",
                        "value": 647
                    },
                    "status": "OK"
                },
                {
                    "distance": {
                        "text": "0.9 km",
                        "value": 888
                    },
                    "duration": {
                        "text": "12 mins",
                        "value": 715
                    },
                    "status": "OK"
                }
            ]
        },
        {
            "elements": [
                {
                    "distance": {
                        "text": "0.7 km",
                        "value": 673
                    },
                    "duration": {
                        "text": "9 mins",
                        "value": 526
                    },
                    "status": "OK"
                },
                {
                    "distance": {
                        "text": "2.9 km",
                        "value": 2913
                    },
                    "duration": {
                        "text": "38 mins",
                        "value": 2296
                    },
                    "status": "OK"
                },
                {
                    "distance": {
                        "text": "2.8 km",
                        "value": 2794
                    },
                    "duration": {
                        "text": "37 mins",
                        "value": 2191
                    },
                    "status": "OK"
                },
                {
                    "distance": {
                        "text": "1.8 km",
                        "value": 1768
                    },
                    "duration": {
                        "text": "25 mins",
                        "value": 1510
                    },
                    "status": "OK"
                },
                {
                    "distance": {
                        "text": "1.3 km",
                        "value": 1290
                    },
                    "duration": {
                        "text": "18 mins",
                        "value": 1084
                    },
                    "status": "OK"
                },
                {
                    "distance": {
                        "text": "1.4 km",
                        "value": 1395
                    },
                    "duration": {
                        "text": "20 mins",
                        "value": 1175
                    },
                    "status": "OK"
                },
                {
                    "distance": {
                        "text": "1.2 km",
                        "value": 1245
                    },
                    "duration": {
                        "text": "18 mins",
                        "value": 1051
                    },
                    "status": "OK"
                },
                {
                    "distance": {
                        "text": "2.0 km",
                        "value": 2023
                    },
                    "duration": {
                        "text": "25 mins",
                        "value": 1491
                    },
                    "status": "OK"
                },
                {
                    "distance": {
                        "text": "1.2 km",
                        "value": 1193
                    },
                    "duration": {
                        "text": "16 mins",
                        "value": 984
                    },
                    "status": "OK"
                },
                {
                    "distance": {
                        "text": "1.3 km",
                        "value": 1272
                    },
                    "duration": {
                        "text": "18 mins",
                        "value": 1052
                    },
                    "status": "OK"
                }
            ]
        },
        {
            "elements": [
                {
                    "distance": {
                        "text": "1.2 km",
                        "value": 1219
                    },
                    "duration": {
                        "text": "15 mins",
                        "value": 920
                    },
                    "status": "OK"
                },
                {
                    "distance": {
                        "text": "2.7 km",
                        "value": 2686
                    },
                    "duration": {
                        "text": "35 mins",
                        "value": 2092
                    },
                    "status": "OK"
                },
                {
                    "distance": {
                        "text": "2.6 km",
                        "value": 2584
                    },
                    "duration": {
                        "text": "34 mins",
                        "value": 2013
                    },
                    "status": "OK"
                },
                {
                    "distance": {
                        "text": "1.1 km",
                        "value": 1135
                    },
                    "duration": {
                        "text": "16 mins",
                        "value": 969
                    },
                    "status": "OK"
                },
                {
                    "distance": {
                        "text": "0.7 km",
                        "value": 689
                    },
                    "duration": {
                        "text": "9 mins",
                        "value": 557
                    },
                    "status": "OK"
                },
                {
                    "distance": {
                        "text": "0.8 km",
                        "value": 807
                    },
                    "duration": {
                        "text": "11 mins",
                        "value": 651
                    },
                    "status": "OK"
                },
                {
                    "distance": {
                        "text": "0.6 km",
                        "value": 644
                    },
                    "duration": {
                        "text": "9 mins",
                        "value": 523
                    },
                    "status": "OK"
                },
                {
                    "distance": {
                        "text": "2.4 km",
                        "value": 2412
                    },
                    "duration": {
                        "text": "30 mins",
                        "value": 1816
                    },
                    "status": "OK"
                },
                {
                    "distance": {
                        "text": "0.6 km",
                        "value": 561
                    },
                    "duration": {
                        "text": "7 mins",
                        "value": 444
                    },
                    "status": "OK"
                },
                {
                    "distance": {
                        "text": "0.6 km",
                        "value": 640
                    },
                    "duration": {
                        "text": "9 mins",
                        "value": 511
                    },
                    "status": "OK"
                }
            ]
        }
    ],
    "status": "OK"
}